Metadata-Version: 2.0
Name: odoo10-addon-datetime-formatter
Version: 10.0.1.0.0
Summary: Helper functions to give correct format to date[time] fields
Home-page: https://www.tecnativa.com
Author: Grupo ESOC Ingeniería de Servicios, Tecnativa,Odoo Community Association (OCA)
Author-email: support@odoo-community.org
License: AGPL-3
Platform: UNKNOWN
Classifier: Programming Language :: Python :: 2.7
Classifier: Framework :: Odoo
Classifier: License :: OSI Approved :: GNU Affero General Public License v3
Requires-Dist: odoo (<10.1dev,>=10.0)
